kernelagent/__init__.py
kernelagent-0.1.0.dist-info/METADATA
kernelagent-0.1.0.dist-info/WHEEL
kernelagent-0.1.0.dist-info/top_level.txt
kernelagent-0.1.0.dist-info/RECORD
